pyramid_helpers/__init__.py
pyramid_helpers/api_doc.py
pyramid_helpers/auth.py
pyramid_helpers/forms/__init__.py
pyramid_helpers/forms/articles.py
pyramid_helpers/forms/auth.py
pyramid_helpers/forms/validators.py
pyramid_helpers/funcs/__init__.py
pyramid_helpers/funcs/articles.py
pyramid_helpers/i18n.py
pyramid_helpers/ldap.py
pyramid_helpers/locale/fr/LC_MESSAGES/pyramid-helpers.mo
pyramid_helpers/models/__init__.py
pyramid_helpers/models/articles.py
pyramid_helpers/models/core.py
pyramid_helpers/paginate.py
pyramid_helpers/predicates.py
pyramid_helpers/radius.py
pyramid_helpers/renderers.py
pyramid_helpers/resources.py
pyramid_helpers/scripts/__init__.py
pyramid_helpers/scripts/initializedb.py
pyramid_helpers/sql_utils.py
pyramid_helpers/static/css/api-doc-bs3.css
pyramid_helpers/static/css/api-doc-bs4.css
pyramid_helpers/static/css/api-doc-bs5.css
pyramid_helpers/static/css/sign-in.css
pyramid_helpers/static/favicon.ico
pyramid_helpers/static/js/api-doc.js
pyramid_helpers/static/js/pyramid-helpers.globals.js
pyramid_helpers/static/js/pyramid-helpers.js
pyramid_helpers/static/translations/fr.js
pyramid_helpers/templates/api-doc-bs3.mako
pyramid_helpers/templates/api-doc-bs4.mako
pyramid_helpers/templates/api-doc-bs5.mako
pyramid_helpers/templates/articles/list.mako
pyramid_helpers/templates/articles/modify.mako
pyramid_helpers/templates/articles/search.mako
pyramid_helpers/templates/articles/visual.mako
pyramid_helpers/templates/auth/sign-in.mako
pyramid_helpers/templates/auth/sign-out.mako
pyramid_helpers/templates/confirm.mako
pyramid_helpers/templates/errors.mako
pyramid_helpers/templates/form-tags.mako
pyramid_helpers/templates/i18n.mako
pyramid_helpers/templates/index.mako
pyramid_helpers/templates/paginate.mako
pyramid_helpers/templates/predicates.mako
pyramid_helpers/templates/site.mako
pyramid_helpers/templates/validators.mako
pyramid_helpers/utils.py
pyramid_helpers/views/__init__.py
pyramid_helpers/views/api/__init__.py
pyramid_helpers-2.1.0.dist-info/WHEEL
pyramid_helpers-2.1.0.dist-info/entry_points.txt
pyramid_helpers-2.1.0.dist-info/METADATA
pyramid_helpers-2.1.0.dist-info/RECORD
