Metadata-Version: 2.3
Name: pyramid-helpers
Version: 2.1.0
Summary: Helpers to develop Pyramid applications
Keywords: web,wsgi,pylons,pyramid,helpers
Author: Cyril Lacoux, Valéry Febvre
Author-email: Cyril Lacoux <clacoux@easter-eggs.com>, Valéry Febvre <vfebvre@easter-eggs.com>
License: AGPL-3.0-or-later
Classifier: License :: OSI Approved :: GNU Affero General Public License v3 or later (AGPLv3+)
Classifier: Development Status :: 5 - Production/Stable
Classifier: Programming Language :: Python
Classifier: Programming Language :: Python :: 3
Classifier: Programming Language :: Python :: 3.9
Classifier: Programming Language :: Python :: 3.10
Classifier: Programming Language :: Python :: 3.11
Classifier: Programming Language :: Python :: 3.12
Classifier: Programming Language :: Python :: 3.13
Classifier: Framework :: Pyramid
Classifier: Topic :: Internet :: WWW/HTTP :: WSGI :: Application
Classifier: Topic :: Internet :: WWW/HTTP :: WSGI
Classifier: Topic :: Internet :: WWW/HTTP
Classifier: Intended Audience :: Developers
Requires-Dist: babel>=2.9,<3.0
Requires-Dist: colorlog>=6.0,<7.0
Requires-Dist: decorator>=5.0,<6.0
Requires-Dist: formencode>=2.0,<3.0
Requires-Dist: mako>=1.1,<2.0
Requires-Dist: passlib>=1.7,<2.0
Requires-Dist: pyramid>=2.0,<3.0
Requires-Dist: pyramid-beaker>=0.9,<1.0
Requires-Dist: pyramid-exclog>=1.0,<2.0
Requires-Dist: pyramid-mako>=1.1,<2.0
Requires-Dist: pyramid-tm>=2.4,<3.0
Requires-Dist: transaction>=5.0,<6.0
Requires-Dist: webob>=1.8,<2.0
Requires-Dist: python-ldap>=3.2,<4.0 ; extra == 'ldap'
Requires-Dist: markdown>=3.1,<4.0 ; extra == 'markdown'
Requires-Dist: psycopg2-binary>=2.9,<3.0 ; extra == 'pgsql-bin'
Requires-Dist: psycopg2>=2.9,<3.0 ; extra == 'pgsql-src'
Requires-Dist: pyrad>=2.1,<3.0 ; extra == 'radius'
Requires-Python: >=3.9, <4.0
Project-URL: download, https://gitlab.com/yack/pyramid-helpers/-/releases
Project-URL: homepage, https://gitlab.com/yack/pyramid-helpers
Project-URL: issues, https://gitlab.com/yack/pyramid-helpers/-/issues
Project-URL: source, https://gitlab.com/yack/pyramid-helpers
Provides-Extra: ldap
Provides-Extra: markdown
Provides-Extra: pgsql-bin
Provides-Extra: pgsql-src
Provides-Extra: radius
